gee_acolite/__init__.py
gee_acolite/bathymetry.py
gee_acolite/correction.py
gee_acolite/water_quality.py
gee_acolite/sensors/__init__.py
gee_acolite/sensors/sentinel2.py
gee_acolite/utils/__init__.py
gee_acolite/utils/l1_convert.py
gee_acolite/utils/masks.py
gee_acolite/utils/search.py
gee_acolite-1.0.1.dist-info/licenses/LICENSE
gee_acolite-1.0.1.dist-info/METADATA
gee_acolite-1.0.1.dist-info/WHEEL
gee_acolite-1.0.1.dist-info/top_level.txt
gee_acolite-1.0.1.dist-info/RECORD
