Metadata-Version: 2.4
Name: gee_acolite
Version: 1.0.1
Summary: ACOLITE atmospheric correction for Google Earth Engine
Author-email: Aouei <sergiohercar1@gmail.com>
License-Expression: GPL-3.0-or-later
Project-URL: Homepage, https://github.com/Aouei/gee_acolite
Project-URL: Documentation, https://github.com/Aouei/gee_acolite
Project-URL: Repository, https://github.com/Aouei/gee_acolite
Project-URL: Bug Tracker, https://github.com/Aouei/gee_acolite/issues
Keywords: earth-engine,atmospheric-correction,acolite,sentinel-2,remote-sensing,water-quality
Classifier: Development Status :: 5 - Production/Stable
Classifier: Intended Audience :: Science/Research
Classifier: Topic :: Scientific/Engineering :: GIS
Classifier: Topic :: Scientific/Engineering :: Atmospheric Science
Classifier: Programming Language :: Python :: 3
Classifier: Programming Language :: Python :: 3.8
Classifier: Programming Language :: Python :: 3.9
Classifier: Programming Language :: Python :: 3.10
Classifier: Programming Language :: Python :: 3.11
Classifier: Operating System :: OS Independent
Requires-Python: >=3.11
License-File: LICENSE
Requires-Dist: earthengine-api>=0.1.350
Requires-Dist: numpy>=1.20.0
Requires-Dist: scipy>=1.7.0
Requires-Dist: netcdf4>=1.7.0
Dynamic: license-file
